meta_analysis/__init__.py
meta_analysis/meta_analysis.py
meta_analysis/example/input.txt
meta_analysis/example/real.txt
meta_analysis-1.2.dist-info/licenses/LICENSE
meta_analysis-1.2.dist-info/METADATA
meta_analysis-1.2.dist-info/WHEEL
meta_analysis-1.2.dist-info/entry_points.txt
meta_analysis-1.2.dist-info/top_level.txt
meta_analysis-1.2.dist-info/RECORD
