Metadata-Version: 2.4
Name: meta-analysis
Version: 1.2
Summary: A package for meta-analysis of studies with complex knowledge and unexplained heterogeneity
Author-email: Martin Adamcik <maths38@gmail.com>
License-Expression: GPL-3.0-or-later
Project-URL: Homepage, https://github.com/maths38/meta-analysis_package
Project-URL: Source, https://github.com/maths38/meta-analysis_package
Keywords: meta-analysis,complex knowledge,heterogeneity
Classifier: Programming Language :: Python :: 3
Classifier: Operating System :: OS Independent
Requires-Python: >=3.12
License-File: LICENSE
Requires-Dist: numpy
Requires-Dist: scipy
Dynamic: license-file
